[
  {
    "_id": "5bdc3743a436bfc18ba47fd1",
    "index": 0,
    "guid": "823efc91-0de8-4544-a998-4f1623b02f04",
    "isActive": false,
    "balance": "$1,906.54",
    "picture": "http://placehold.it/32x32",
    "age": 28,
    "eyeColor": "brown",
    "name": "Dominguez Bishop",
    "gender": "male",
    "company": "ACUSAGE",
    "email": "dominguezbishop@acusage.com",
    "phone": "+1 (875) 491-3188",
    "address": "425 Tech Place, Hayden, Virginia, 3030",
    "about": "Amet aute cillum nulla mollit reprehenderit fugiat laborum. Cillum ea in qui ea excepteur do. Qui fugiat amet deserunt incididunt sint esse magna excepteur adipisicing. Laboris labore deserunt duis mollit. Sint reprehenderit labore enim ipsum laborum culpa cupidatat aliqua fugiat consectetur ullamco esse anim.\r\n",
    "registered": "2014-05-26T10:25:10 -04:00",
    "latitude": -5.258579,
    "longitude": 86.532854,
    "tags": [
      "duis",
      "sint",
      "quis",
      "ad",
      "deserunt",
      "exercitation",
      "laboris"
    ],
    "friends": [
      {
        "id": 0,
        "name": "Pittman Carney"
      },
      {
        "id": 1,
        "name": "Baker Foster"
      },
      {
        "id": 2,
        "name": "Decker Mooney"
      }
    ],
    "greeting": "Hello, Dominguez Bishop! You have 4 unread messages.",
    "favoriteFruit": "apple"
  },
  {
    "_id": "5bdc37431fd44ba1c642d46d",
    "index": 1,
    "guid": "f037e718-a6ef-4d1b-b259-d1e67ef82d35",
    "isActive": false,
    "balance": "$2,325.49",
    "picture": "http://placehold.it/32x32",
    "age": 22,
    "eyeColor": "blue",
    "name": "Lidia Griffith",
    "gender": "female",
    "company": "AMTAS",
    "email": "lidiagriffith@amtas.com",
    "phone": "+1 (975) 432-3462",
    "address": "949 Bradford Street, Henrietta, Nebraska, 6115",
    "about": "Excepteur fugiat occaecat incididunt veniam ea nulla veniam non cillum voluptate irure ut eu commodo. Consequat ad aute eu aliquip officia dolor Lorem ea dolore occaecat. Nisi dolore voluptate veniam magna nisi nulla exercitation id enim veniam eiusmod ea in qui. Voluptate qui sunt elit officia amet nulla quis sit elit sunt amet adipisicing veniam consequat. Non aute minim esse excepteur. Cupidatat enim qui nulla labore velit labore pariatur laboris tempor Lorem anim.\r\n",
    "registered": "2014-12-10T01:49:52 -04:00",
    "latitude": 84.80207,
    "longitude": 84.223125,
    "tags": [
      "adipisicing",
      "minim",
      "elit",
      "commodo",
      "nulla",
      "sint",
      "veniam"
    ],
    "friends": [
      {
        "id": 0,
        "name": "Nicole Morse"
      },
      {
        "id": 1,
        "name": "Booth Moses"
      },
      {
        "id": 2,
        "name": "Isabel Guzman"
      }
    ],
    "greeting": "Hello, Lidia Griffith! You have 2 unread messages.",
    "favoriteFruit": "strawberry"
  },
  {
    "_id": "5bdc37438ff6c2fc34b647e3",
    "index": 2,
    "guid": "4e8ac6be-a714-48ba-9761-d64633fff3c8",
    "isActive": false,
    "balance": "$2,012.16",
    "picture": "http://placehold.it/32x32",
    "age": 34,
    "eyeColor": "brown",
    "name": "Hall Burton",
    "gender": "male",
    "company": "NURPLEX",
    "email": "hallburton@nurplex.com",
    "phone": "+1 (800) 406-2867",
    "address": "733 Suydam Place, Taycheedah, Idaho, 8872",
    "about": "Consequat adipisicing eu eiusmod do nostrud. Pariatur culpa reprehenderit veniam sunt cillum. Est ipsum consectetur laboris officia nisi duis non ea officia dolore.\r\n",
    "registered": "2018-03-08T01:29:41 -04:00",
    "latitude": 83.827054,
    "longitude": 22.169061,
    "tags": [
      "culpa",
      "ex",
      "reprehenderit",
      "ea",
      "velit",
      "aliquip",
      "id"
    ],
    "friends": [
      {
        "id": 0,
        "name": "Wright Hensley"
      },
      {
        "id": 1,
        "name": "Mae Cabrera"
      },
      {
        "id": 2,
        "name": "Briana Kerr"
      }
    ],
    "greeting": "Hello, Hall Burton! You have 4 unread messages.",
    "favoriteFruit": "apple"
  },
  {
    "_id": "5bdc37434af4fd9d430c8fd3",
    "index": 3,
    "guid": "00de2c39-512f-4b8f-8ef2-307fb7fc3a44",
    "isActive": false,
    "balance": "$1,252.50",
    "picture": "http://placehold.it/32x32",
    "age": 29,
    "eyeColor": "blue",
    "name": "Golden Kim",
    "gender": "male",
    "company": "FREAKIN",
    "email": "goldenkim@freakin.com",
    "phone": "+1 (917) 596-3847",
    "address": "682 Coffey Street, Worcester, Puerto Rico, 8183",
    "about": "Occaecat anim irure eu consectetur ea fugiat ea consequat. Eu culpa veniam dolore qui fugiat excepteur nulla eu. Et id qui id consectetur id do eiusmod occaecat laborum.\r\n",
    "registered": "2016-06-01T06:08:39 -04:00",
    "latitude": -55.243622,
    "longitude": 25.276316,
    "tags": [
      "officia",
      "nostrud",
      "enim",
      "labore",
      "veniam",
      "labore",
      "dolore"
    ],
    "friends": [
      {
        "id": 0,
        "name": "Brock Moody"
      },
      {
        "id": 1,
        "name": "Petra Moreno"
      },
      {
        "id": 2,
        "name": "Ramos Guerra"
      }
    ],
    "greeting": "Hello, Golden Kim! You have 8 unread messages.",
    "favoriteFruit": "banana"
  },
  {
    "_id": "5bdc37432cd7e7bdf018687e",
    "index": 4,
    "guid": "76c7f057-524e-4358-951e-5773dcd5b9e4",
    "isActive": true,
    "balance": "$3,772.46",
    "picture": "http://placehold.it/32x32",
    "age": 28,
    "eyeColor": "green",
    "name": "Jacqueline Solis",
    "gender": "female",
    "company": "ZORROMOP",
    "email": "jacquelinesolis@zorromop.com",
    "phone": "+1 (832) 407-3184",
    "address": "704 Auburn Place, Roland, Georgia, 6234",
    "about": "Anim non eu tempor officia ullamco excepteur qui sit cupidatat velit officia exercitation esse pariatur. Non cupidatat ad nisi aliqua laborum. Consectetur est irure est esse non aliqua sint ut pariatur. Fugiat aliqua consequat id aliquip labore irure dolore commodo amet minim consectetur ea excepteur. Irure aliquip sint aliqua consectetur tempor ad adipisicing. Culpa adipisicing culpa mollit ad veniam eiusmod proident ex do adipisicing. Mollit nostrud dolor reprehenderit reprehenderit laborum aliqua excepteur qui.\r\n",
    "registered": "2018-08-09T11:51:22 -04:00",
    "latitude": -18.66595,
    "longitude": 92.837296,
    "tags": [
      "officia",
      "irure",
      "Lorem",
      "minim",
      "nostrud",
      "proident",
      "tempor"
    ],
    "friends": [
      {
        "id": 0,
        "name": "Winifred Fischer"
      },
      {
        "id": 1,
        "name": "Good Elliott"
      },
      {
        "id": 2,
        "name": "Price Rivas"
      }
    ],
    "greeting": "Hello, Jacqueline Solis! You have 9 unread messages.",
    "favoriteFruit": "banana"
  },
  {
    "_id": "5bdc3743f32395e237c86833",
    "index": 5,
    "guid": "9299c394-fade-4809-9bb5-4cfcc9d43cab",
    "isActive": false,
    "balance": "$3,141.09",
    "picture": "http://placehold.it/32x32",
    "age": 26,
    "eyeColor": "green",
    "name": "Essie Rosales",
    "gender": "female",
    "company": "BUZZMAKER",
    "email": "essierosales@buzzmaker.com",
    "phone": "+1 (810) 547-3876",
    "address": "102 Kane Place, Draper, Florida, 1639",
    "about": "Lorem est duis dolor enim eiusmod aliqua nisi fugiat. Consectetur eiusmod exercitation enim irure ex velit. Aliquip in sint veniam aute aute dolore laborum culpa irure ex qui eu sunt. Ad sit ea id dolor sit.\r\n",
    "registered": "2016-01-14T12:10:01 -04:00",
    "latitude": -16.310991,
    "longitude": 62.087261,
    "tags": [
      "fugiat",
      "proident",
      "id",
      "veniam",
      "tempor",
      "ut",
      "sit"
    ],
    "friends": [
      {
        "id": 0,
        "name": "Darlene Casey"
      },
      {
        "id": 1,
        "name": "Walsh Cooper"
      },
      {
        "id": 2,
        "name": "Goodman Fisher"
      }
    ],
    "greeting": "Hello, Essie Rosales! You have 8 unread messages.",
    "favoriteFruit": "banana"
  }
]